README.md
setup.py
rulebook/__init__.py
rulebook/change.py
rulebook/check.py
rulebook/core.py
rulebook/trying.py
rulebook/utils.py
rulebook.egg-info/PKG-INFO
rulebook.egg-info/SOURCES.txt
rulebook.egg-info/dependency_links.txt
rulebook.egg-info/top_level.txt